Metadata-Version: 1.0
Name: Pranay-Udacity-distributions
Version: 0.1
Summary: Gaussian and Binomial distributions
Home-page: UNKNOWN
Author: Pranay Barkataki
Author-email: pranay.barkataki@gmail.com
License: UNKNOWN
Platform: UNKNOWN
